CHANGES.txt
LICENSE.txt
MANIFEST.in
README.txt
setup.py
VerConChk.egg-info/PKG-INFO
VerConChk.egg-info/SOURCES.txt
VerConChk.egg-info/dependency_links.txt
VerConChk.egg-info/top_level.txt
bin/vcc
docs/index.rst
docs/internals.rst
docs/usage.rst
verconchk/__init__.py
verconchk/repository.py
verconchk/ui.py
verconchk/tests/__init__.py
verconchk/tests/test_repository.py