Metadata-Version: 1.0
Name: VerConChk
Version: 1.0
Summary: a tool for finding and checking the status of version controlled files
Home-page: http://bitbucket.org/ddbeck/verconchk/
Author: Daniel D. Beck
Author-email: me@danieldbeck.com
License: LICENSE.txt
Platform: UNKNOWN
